eqnet/__init__.py
eqnet/data/__init__.py
eqnet/data/das.py
eqnet/data/quakeflow_nc.py
eqnet/data/seismic_network.py
eqnet/data/seismic_trace.py
eqnet/data/transforms.py
eqnet/models/__init__.py
eqnet/models/_utils.py
eqnet/models/autoencoder.py
eqnet/models/eqnet.py
eqnet/models/phasenet.py
eqnet/models/phasenet_das.py
eqnet/models/phasenet_das_plus.py
eqnet/models/phasenet_plus.py
eqnet/models/phasenet_prompt.py
eqnet/models/phasenet_tf.py
eqnet/models/phasenet_tf_plus.py
eqnet/models/resnet1d.py
eqnet/models/swin_transformer.py
eqnet/models/swin_transformer_v2.py
eqnet/models/unet.py
eqnet/models/unet_bak.py
eqnet/models/vae.py
eqnet/models/x_unet.py
eqnet/models/prompt/__init__.py
eqnet/models/prompt/common.py
eqnet/models/prompt/mask_decoder.py
eqnet/models/prompt/prompt_encoder.py
eqnet/models/prompt/transformer.py
eqnet/utils/__init__.py
eqnet/utils/postprocess.py
eqnet/utils/station_sampler.py
eqnet/utils/visualization.py
eqnet-0.1.8.dist-info/licenses/LICENSE
eqnet-0.1.8.dist-info/METADATA
eqnet-0.1.8.dist-info/WHEEL
eqnet-0.1.8.dist-info/top_level.txt
eqnet-0.1.8.dist-info/RECORD
