Metadata-Version: 2.4
Name: EQNet
Version: 0.1.8
License-File: LICENSE
Requires-Dist: torch
Requires-Dist: h5py
Requires-Dist: matplotlib
Requires-Dist: pandas
Dynamic: description
Dynamic: description-content-type
Dynamic: license-file
Dynamic: requires-dist
